tensorhue/__init__.py
tensorhue/_print_opts.py
tensorhue/colors.py
tensorhue/converters.py
tensorhue/eastereggs.py
tensorhue/py.typed
tensorhue/viz.py
tensorhue-0.1.0.dist-info/METADATA
tensorhue-0.1.0.dist-info/WHEEL
tensorhue-0.1.0.dist-info/top_level.txt
tensorhue-0.1.0.dist-info/RECORD
