Metadata-Version: 2.1
Name: tensorhue
Version: 0.1.0
Summary: TensorHue lets you visualize tensors in your console.
Author: epistoteles
Author-email: <korbinian.koch@uni-hamburg.de>
Classifier: Development Status :: 3 - Alpha
Classifier: Intended Audience :: Developers
Classifier: Programming Language :: Python :: 3
Classifier: Operating System :: Unix
Classifier: Operating System :: MacOS :: MacOS X
Classifier: Operating System :: Microsoft :: Windows
Requires-Python: >=3.7
Requires-Dist: numpy
Requires-Dist: rich
Requires-Dist: matplotlib
Provides-Extra: testing
Requires-Dist: pre-commit; extra == "testing"
Requires-Dist: pylint; extra == "testing"
Requires-Dist: torch; extra == "testing"
Requires-Dist: tox; extra == "testing"
Requires-Dist: pytest; extra == "testing"
Requires-Dist: pytest-cov; extra == "testing"
Requires-Dist: mypy; extra == "testing"
Requires-Dist: flake8; extra == "testing"
